e2b_devcontainers/__init__.py
e2b_devcontainers/devcontainers_async.py
e2b_devcontainers/devcontainers_sync.py
e2b_devcontainers/utils.py
e2b_devcontainers-0.1.3.dist-info/METADATA
e2b_devcontainers-0.1.3.dist-info/WHEEL
e2b_devcontainers-0.1.3.dist-info/top_level.txt
e2b_devcontainers-0.1.3.dist-info/RECORD
